{
  "id": "RAAB",
  "number": 80,
  "fromZero": true,
  "hasSecret": true,
  "name": "『遊戯王OCG デュエルモンスターズ RAGE OF THE ABYSS』",
  "desc": "●発売日／2024年7月27日（土）\n●メーカー／KONAMI\n●価格／1パック5枚入り176円（税込）\n　 　   　 1ボックス30パック入り",
  "list": [{"id":"","number":"RAAB-JP000","type":"","name":"","rare":"","desc":""},{"id":"","number":"RAAB-JP001","type":"","name":"","rare":"","desc":""},{"id":"","number":"RAAB-JP002","type":"","name":"","rare":"","desc":""},{"id":"","number":"RAAB-JP003","type":"","name":"","rare":"","desc":""},{"id":"","number":"RAAB-JP004","type":"","name":"","rare":"","desc":""},{"id":"","number":"RAAB-JP005","type":"","name":"","rare":"","desc":""},{"id":"","number":"RAAB-JP006","type":"","name":"","rare":"","desc":""},{"id":"","number":"RAAB-JP007","type":"","name":"","rare":"","desc":""},{"id":"","number":"RAAB-JP008","type":"","name":"","rare":"","desc":""},{"id":"","number":"RAAB-JP009","type":"","name":"","rare":"","desc":""},{"id":"","number":"RAAB-JP010","type":"","name":"","rare":"","desc":""},{"id":"","number":"RAAB-JP011","type":"","name":"","rare":"","desc":""},{"id":"","number":"RAAB-JP012","type":"","name":"","rare":"","desc":""},{"id":"","number":"RAAB-JP013","type":"","name":"","rare":"","desc":""},{"id":"","number":"RAAB-JP014","type":"","name":"","rare":"","desc":""},{"id":"","number":"RAAB-JP015","type":"","name":"","rare":"","desc":""},{"id":"","number":"RAAB-JP016","type":"","name":"","rare":"","desc":""},{"id":"","number":"RAAB-JP017","type":"","name":"","rare":"","desc":""},{"id":"","number":"RAAB-JP018","type":"","name":"","rare":"","desc":""},{"id":"","number":"RAAB-JP019","type":"","name":"","rare":"","desc":""},{"id":"","number":"RAAB-JP020","type":"","name":"","rare":"","desc":""},{"id":"","number":"RAAB-JP021","type":"","name":"","rare":"","desc":""},{"id":"","number":"RAAB-JP022","type":"","name":"","rare":"","desc":""},{"id":"","number":"RAAB-JP023","type":"","name":"","rare":"","desc":""},{"id":"","number":"RAAB-JP024","type":"","name":"","rare":"","desc":""},{"id":"","number":"RAAB-JP025","type":"","name":"","rare":"","desc":""},{"id":"","number":"RAAB-JP026","type":"","name":"","rare":"","desc":""},{"id":"","number":"RAAB-JP027","type":"","name":"","rare":"","desc":""},{"id":"","number":"RAAB-JP028","type":"","name":"","rare":"","desc":""},{"id":"","number":"RAAB-JP029","type":"","name":"","rare":"","desc":""},{"id":"","number":"RAAB-JP030","type":"","name":"","rare":"","desc":""},{"id":"","number":"RAAB-JP031","type":"","name":"","rare":"","desc":""},{"id":"","number":"RAAB-JP032","type":"","name":"","rare":"","desc":""},{"id":"","number":"RAAB-JP033","type":"","name":"","rare":"","desc":""},{"id":"","number":"RAAB-JP034","type":"","name":"","rare":"","desc":""},{"id":"","number":"RAAB-JP035","type":"","name":"","rare":"","desc":""},{"id":"","number":"RAAB-JP036","type":"","name":"","rare":"","desc":""},{"id":"","number":"RAAB-JP037","type":"","name":"","rare":"","desc":""},{"id":"","number":"RAAB-JP038","type":"","name":"","rare":"","desc":""},{"id":"","number":"RAAB-JP039","type":"","name":"","rare":"","desc":""},{"id":"","number":"RAAB-JP040","type":"","name":"","rare":"","desc":""},{"id":"","number":"RAAB-JP041","type":"","name":"","rare":"","desc":""},{"id":"","number":"RAAB-JP042","type":"","name":"","rare":"","desc":""},{"id":"","number":"RAAB-JP043","type":"","name":"","rare":"","desc":""},{"id":"","number":"RAAB-JP044","type":"","name":"","rare":"","desc":""},{"id":"","number":"RAAB-JP045","type":"","name":"","rare":"","desc":""},{"id":"","number":"RAAB-JP046","type":"","name":"","rare":"","desc":""},{"id":"","number":"RAAB-JP047","type":"","name":"","rare":"","desc":""},{"id":"","number":"RAAB-JP048","type":"","name":"","rare":"","desc":""},{"id":"","number":"RAAB-JP049","type":"","name":"","rare":"","desc":""},{"id":"","number":"RAAB-JP050","type":"","name":"","rare":"","desc":""},{"id":"","number":"RAAB-JP051","type":"","name":"","rare":"","desc":""},{"id":"","number":"RAAB-JP052","type":"","name":"","rare":"","desc":""},{"id":"","number":"RAAB-JP053","type":"","name":"","rare":"","desc":""},{"id":"","number":"RAAB-JP054","type":"","name":"","rare":"","desc":""},{"id":"","number":"RAAB-JP055","type":"","name":"","rare":"","desc":""},{"id":"","number":"RAAB-JP056","type":"","name":"","rare":"","desc":""},{"id":"","number":"RAAB-JP057","type":"","name":"","rare":"","desc":""},{"id":"","number":"RAAB-JP058","type":"","name":"","rare":"","desc":""},{"id":"","number":"RAAB-JP059","type":"","name":"","rare":"","desc":""},{"id":"","number":"RAAB-JP060","type":"","name":"","rare":"","desc":""},{"id":"","number":"RAAB-JP061","type":"","name":"","rare":"","desc":""},{"id":"","number":"RAAB-JP062","type":"","name":"","rare":"","desc":""},{"id":"","number":"RAAB-JP063","type":"","name":"","rare":"","desc":""},{"id":"","number":"RAAB-JP064","type":"","name":"","rare":"","desc":""},{"id":"","number":"RAAB-JP065","type":"","name":"","rare":"","desc":""},{"id":"","number":"RAAB-JP066","type":"","name":"","rare":"","desc":""},{"id":"","number":"RAAB-JP067","type":"","name":"","rare":"","desc":""},{"id":"","number":"RAAB-JP068","type":"","name":"","rare":"","desc":""},{"id":"","number":"RAAB-JP069","type":"","name":"","rare":"","desc":""},{"id":"","number":"RAAB-JP070","type":"","name":"","rare":"","desc":""},{"id":"","number":"RAAB-JP071","type":"","name":"","rare":"","desc":""},{"id":"","number":"RAAB-JP072","type":"","name":"","rare":"","desc":""},{"id":"","number":"RAAB-JP073","type":"","name":"","rare":"","desc":""},{"id":"","number":"RAAB-JP074","type":"","name":"","rare":"","desc":""},{"id":"","number":"RAAB-JP075","type":"","name":"","rare":"","desc":""},{"id":"","number":"RAAB-JP076","type":"","name":"","rare":"","desc":""},{"id":"","number":"RAAB-JP077","type":"","name":"","rare":"","desc":""},{"id":"","number":"RAAB-JP078","type":"","name":"","rare":"","desc":""},{"id":"","number":"RAAB-JP079","type":"","name":"","rare":"","desc":""},{"id":"","number":"RAAB-JP080","type":"","name":"","rare":"","desc":""}]
}
